cgmquantify/__init__.py
cgmquantify_updated-0.5.3.dist-info/LICENSE
cgmquantify_updated-0.5.3.dist-info/METADATA
cgmquantify_updated-0.5.3.dist-info/WHEEL
cgmquantify_updated-0.5.3.dist-info/top_level.txt
cgmquantify_updated-0.5.3.dist-info/RECORD
