Metadata-Version: 2.1
Name: cgmquantify_updated
Version: 0.5.3
Summary: Quantifying glucose and glucose variability from CGM devices
Home-page: https://github.com/MengdeLiu/CGM_quantify
Download-URL: https://github.com/yourusername/yourrepo/archive/refs/tags/v0.5.1.tar.gz
Author: Brinnae Bent
Author-email: bmbent@ncsu.edu
License: MIT
License-File: LICENSE
Requires-Dist: pandas
Requires-Dist: numpy
Requires-Dist: matplotlib
Requires-Dist: datetime
Requires-Dist: statsmodels
